conan_check_updates/__init__.py
conan_check_updates/__main__.py
conan_check_updates/cli.py
conan_check_updates/color.py
conan_check_updates/conan.py
conan_check_updates/filter.py
conan_check_updates/main.py
conan_check_updates/version.py
conan_check_updates-0.3.0.dist-info/LICENSE
conan_check_updates-0.3.0.dist-info/METADATA
conan_check_updates-0.3.0.dist-info/WHEEL
conan_check_updates-0.3.0.dist-info/entry_points.txt
conan_check_updates-0.3.0.dist-info/top_level.txt
conan_check_updates-0.3.0.dist-info/RECORD
