Metadata-Version: 2.1
Name: conan-check-updates
Version: 0.3.0
Summary: Check for updates of your conanfile.txt/conanfile.py requirements.
Author-email: Lukas Berbuer <lukas.berbuer@gmail.com>
License: MIT License
Project-URL: Changelog, https://github.com/lukasberbuer/conan-check-updates/blob/master/CHANGELOG.md
Project-URL: Source, https://github.com/lukasberbuer/conan-check-updates
Project-URL: Issues, https://github.com/lukasberbuer/conan-check-updates/issues
Keywords: conan,update,upgrade,package,requirements,node-check-updates
Classifier: Development Status :: 4 - Beta
Classifier: Environment :: Console
Classifier: Intended Audience :: Developers
Classifier: License :: OSI Approved :: MIT License
Classifier: Operating System :: OS Independent
Classifier: Programming Language :: C
Classifier: Programming Language :: C++
Classifier: Programming Language :: Python
Classifier: Programming Language :: Python :: 3 :: Only
Classifier: Programming Language :: Python :: 3
Classifier: Programming Language :: Python :: 3.7
Classifier: Programming Language :: Python :: 3.8
Classifier: Programming Language :: Python :: 3.9
Classifier: Programming Language :: Python :: 3.10
Classifier: Programming Language :: Python :: 3.11
Classifier: Programming Language :: Python :: 3.12
Classifier: Topic :: Software Development
Classifier: Topic :: Software Development :: Libraries
Requires-Python: >=3.7
License-File: LICENSE
Requires-Dist: typing-extensions ; python_version < "3.10"
Requires-Dist: importlib-metadata ; python_version < "3.8"
Provides-Extra: dev
Requires-Dist: conan-check-updates[tests,tools] ; extra == 'dev'
Provides-Extra: tests
Requires-Dist: conan >=1.5 ; extra == 'tests'
Requires-Dist: coverage[toml] >=5 ; extra == 'tests'
Requires-Dist: pytest >=6 ; extra == 'tests'
Requires-Dist: pytest-asyncio ; extra == 'tests'
Requires-Dist: pytest-rerunfailures ; extra == 'tests'
Provides-Extra: tools
Requires-Dist: cogapp >=3 ; extra == 'tools'
Requires-Dist: mypy >=0.9 ; extra == 'tools'
Requires-Dist: pre-commit ; extra == 'tools'
Requires-Dist: ruff ; extra == 'tools'
Requires-Dist: tox >=3.4 ; extra == 'tools'
